kalshi_orderbook-0.1.0.dist-info/METADATA
kalshi_orderbook-0.1.0.dist-info/WHEEL
kalshi_orderbook-0.1.0.dist-info/licenses/LICENSE
orderbook/__init__.py
orderbook/analyzer.py
orderbook/orderbook_rs.abi3.so
orderbook/orderbook_rs.pyi
kalshi_orderbook-0.1.0.dist-info/RECORD
