Metadata-Version: 2.4
Name: kalshi-orderbook
Version: 0.1.0
Requires-Dist: duckdb>=1.0.0
Requires-Dist: pandas>=2.0.0
License-File: LICENSE
Requires-Python: >=3.7
